utilities_test/__init__.py
utilities_test/utilities.py
utilities_test-0.2.dist-info/LICENSE.txt
utilities_test-0.2.dist-info/METADATA
utilities_test-0.2.dist-info/WHEEL
utilities_test-0.2.dist-info/top_level.txt
utilities_test-0.2.dist-info/RECORD
