Metadata-Version: 2.1
Name: utilities-test
Version: 0.2
Summary: Utilities
License-File: LICENSE.txt
